{
  "version": "2.2.4",
  "songName": "Grieving (Remnants Mix)",
  "artist": "DagaiTai",
  "charter": "TRWario",
  "divisions": 96,
  "looped": false,
  "offsets": {
    "instrumental": 0,
    "altInstrumentals": {},
    "vocals": {},
    "altVocals": {}
  },
  "playData": {
    "songVariations": [],
    "difficulties": ["easy", "normal", "hard"],
    "characters": {
      "player": "dad-remnants-grieving",
      "girlfriend": "bf-gf-remnants-grieving",
      "opponent": "mom-remnants-grieving",
      "instrumental": "",
      "altInstrumentals": [],
      "opponentVocals": ["mom-remnants-grieving"],
      "playerVocals": ["dad-remnants-grieving"]
    },
    "stage": "grievingRemnants",
    "noteStyle": "funkin",
    "ratings": {
      "easy": 0,
      "normal": 0,
      "hard": 0
    },
    "previewStart": 0,
    "previewEnd": 0
  },
  "generatedBy": "Friday Night Funkin' - v0.8.1",
  "timeFormat": "ms",
  "timeChanges": [
    {
      "t": 0,
      "b": 0,
      "bpm": 70,
      "n": 4,
      "d": 4,
      "bt": [4, 4, 4, 4]
    },
    {
      "t": 43232.2954,
      "b": 50.4377,
      "bpm": 70,
      "n": 4,
      "d": 4,
      "bt": [4, 4, 4, 4]
    },
    {
      "t": 85122,
      "b": 99.309,
      "bpm": 70,
      "n": 4,
      "d": 4,
      "bt": [4, 4, 4, 4]
    },
    {
      "t": 121545.5715,
      "b": 141.8032,
      "bpm": 70,
      "n": 4,
      "d": 4,
      "bt": [4, 4, 4, 4]
    },
    {
      "t": 139879.0001,
      "b": 163.1922,
      "bpm": 70,
      "n": 4,
      "d": 4,
      "bt": [4, 4, 4, 4]
    }
  ]
}
