{"ATLAS": {"SPRITES":[ 
{"SPRITE" : {"name": "0000","x":1830,"y":735,"w":85,"h":86,"rotated": false}},
{"SPRITE" : {"name": "0001","x":102,"y":369,"w":207,"h":164,"rotated": false}},
{"SPRITE" : {"name": "0002","x":383,"y":752,"w":88,"h":57,"rotated": false}},
{"SPRITE" : {"name": "0003","x":1917,"y":784,"w":78,"h":58,"rotated": false}},
{"SPRITE" : {"name": "0004","x":1187,"y":473,"w":131,"h":211,"rotated": false}},
{"SPRITE" : {"name": "0005","x":731,"y":585,"w":139,"h":128,"rotated": false}},
{"SPRITE" : {"name": "0006","x":1163,"y":2,"w":216,"h":240,"rotated": false}},
{"SPRITE" : {"name": "0007","x":1496,"y":711,"w":145,"h":72,"rotated": false}},
{"SPRITE" : {"name": "0008","x":711,"y":715,"w":80,"h":102,"rotated": false}},
{"SPRITE" : {"name": "0009","x":793,"y":789,"w":73,"h":41,"rotated": false}},
{"SPRITE" : {"name": "0010","x":1999,"y":2,"w":11,"h":12,"rotated": false}},
{"SPRITE" : {"name": "0011","x":102,"y":535,"w":76,"h":349,"rotated": false}},
{"SPRITE" : {"name": "0012","x":1747,"y":394,"w":81,"h":384,"rotated": false}},
{"SPRITE" : {"name": "0013","x":1653,"y":388,"w":92,"h":351,"rotated": false}},
{"SPRITE" : {"name": "0014","x":998,"y":353,"w":104,"h":388,"rotated": false}},
{"SPRITE" : {"name": "0015","x":2,"y":369,"w":98,"h":351,"rotated": false}},
{"SPRITE" : {"name": "0016","x":1771,"y":2,"w":112,"h":390,"rotated": false}},
{"SPRITE" : {"name": "0017","x":513,"y":360,"w":107,"h":349,"rotated": false}},
{"SPRITE" : {"name": "0018","x":1653,"y":2,"w":116,"h":384,"rotated": false}},
{"SPRITE" : {"name": "0019","x":879,"y":218,"w":117,"h":355,"rotated": false}},
{"SPRITE" : {"name": "0020","x":1522,"y":2,"w":129,"h":352,"rotated": false}},
{"SPRITE" : {"name": "0021","x":1381,"y":2,"w":139,"h":353,"rotated": false}},
{"SPRITE" : {"name": "0022","x":413,"y":2,"w":178,"h":350,"rotated": false}},
{"SPRITE" : {"name": "0023","x":593,"y":2,"w":166,"h":356,"rotated": false}},
{"SPRITE" : {"name": "0024","x":1011,"y":2,"w":150,"h":349,"rotated": false}},
{"SPRITE" : {"name": "0025","x":1551,"y":356,"w":100,"h":353,"rotated": false}},
{"SPRITE" : {"name": "0026","x":311,"y":369,"w":96,"h":352,"rotated": false}},
{"SPRITE" : {"name": "0027","x":1104,"y":473,"w":81,"h":372,"rotated": false}},
{"SPRITE" : {"name": "0028","x":413,"y":354,"w":98,"h":396,"rotated": false}},
{"SPRITE" : {"name": "0029","x":1885,"y":2,"w":112,"h":387,"rotated": false}},
{"SPRITE" : {"name": "0030","x":622,"y":360,"w":107,"h":339,"rotated": false}},
{"SPRITE" : {"name": "0031","x":761,"y":218,"w":116,"h":365,"rotated": false}},
{"SPRITE" : {"name": "0032","x":961,"y":743,"w":97,"h":58,"rotated": false}},
{"SPRITE" : {"name": "0033","x":1643,"y":741,"w":96,"h":62,"rotated": false}},
{"SPRITE" : {"name": "0034","x":622,"y":701,"w":87,"h":126,"rotated": false}},
{"SPRITE" : {"name": "0035","x":879,"y":575,"w":88,"h":129,"rotated": false}},
{"SPRITE" : {"name": "0036","x":872,"y":706,"w":87,"h":126,"rotated": false}},
{"SPRITE" : {"name": "0037","x":513,"y":711,"w":93,"h":88,"rotated": false}},
{"SPRITE" : {"name": "0038","x":1741,"y":780,"w":75,"h":63,"rotated": false}},
{"SPRITE" : {"name": "0039","x":1496,"y":785,"w":75,"h":60,"rotated": false}},
{"SPRITE" : {"name": "0040","x":2,"y":2,"w":409,"h":365,"rotated": false}},
{"SPRITE" : {"name": "0041","x":2,"y":722,"w":86,"h":88,"rotated": false}},
{"SPRITE" : {"name": "0042","x":1345,"y":357,"w":204,"h":184,"rotated": false}},
{"SPRITE" : {"name": "0043","x":1917,"y":735,"w":127,"h":47,"rotated": false}},
{"SPRITE" : {"name": "0044","x":1479,"y":543,"w":69,"h":51,"rotated": false}},
{"SPRITE" : {"name": "0045","x":793,"y":715,"w":76,"h":72,"rotated": false}},
{"SPRITE" : {"name": "0046","x":180,"y":697,"w":102,"h":111,"rotated": false}},
{"SPRITE" : {"name": "0047","x":1187,"y":694,"w":175,"h":97,"rotated": false}},
{"SPRITE" : {"name": "0048","x":1830,"y":625,"w":164,"h":108,"rotated": false}},
{"SPRITE" : {"name": "0049","x":180,"y":535,"w":127,"h":160,"rotated": false}},
{"SPRITE" : {"name": "0050","x":284,"y":723,"w":97,"h":76,"rotated": false}},
{"SPRITE" : {"name": "0051","x":1885,"y":391,"w":142,"h":232,"rotated": false}},
{"SPRITE" : {"name": "0052","x":761,"y":2,"w":248,"h":214,"rotated": false}},
{"SPRITE" : {"name": "0053","x":1163,"y":244,"w":180,"h":227,"rotated": false}},
{"SPRITE" : {"name": "0054","x":1364,"y":694,"w":130,"h":99,"rotated": false}},
{"SPRITE" : {"name": "0055","x":1320,"y":543,"w":157,"h":149,"rotated": false}}
]},
"meta": {
"app": "Adobe Animate",
"version": "24.0.3.19",
"image": "spritemap1.png",
"format": "RGBA8888",
"size": {"w":2046,"h":886},
"resolution": "1"
}
}
