{
 "version": "2.2.4",
 "songName": "Monster (Remnants Mix)",
 "artist": "Luna (ft. RubyyyButCool)",
 "charter": "The Dee to my house",
 "divisions": 96,
 "looped": false,
 "offsets": {
  "instrumental": 0,
  "altInstrumentals": {  },
  "vocals": {  },
  "altVocals": {  }
 },
 "playData": {
  "songVariations": [],
  "difficulties": [
   "easy",
   "normal",
   "hard"
  ],
  "characters": {
   "player": "bf-remnants-dark",
   "girlfriend": "gf-remnants-dark",
   "opponent": "monster-remnants-dark",
   "instrumental": "remnants",
   "altInstrumentals": [],
   "opponentVocals": [
    "monster-remnants-dark"
   ],
   "playerVocals": [
    "bf-remnants-dark"
   ]
  },
  "stage": "spookyMansionRemnants",
  "noteStyle": "funkin",
  "ratings": {
   "easy": 0,
   "hard": 0,
   "normal": 0
  },
  "album": "remnants-week2-scary",
  "previewStart": 0,
  "previewEnd": 15000
 },
 "generatedBy": "Friday Night Funkin' - v0.7.5 (develop : 5b5d76a) PROTOTYPE",
 "timeFormat": "ms",
 "timeChanges": [
  {
   "t": 0,
   "b": 0,
   "bpm": 106,
   "n": 4,
   "d": 4,
   "bt": [4, 4, 4, 4]
  },
  {
   "t": 62890.3397,
   "b": 111.1063,
   "bpm": 106,
   "n": 4,
   "d": 4,
   "bt": [4, 4, 4, 4]
  },
  {
   "t": 72000,
   "b": 127.2,
   "bpm": 120,
   "n": 4,
   "d": 4,
   "bt": [4, 4, 4, 4]
  },
  {
   "t": 88000,
   "b": 159.2,
   "bpm": 123,
   "n": 4,
   "d": 4,
   "bt": [4, 4, 4, 4]
  },
  {
   "t": 106000,
   "b": 196.1,
   "bpm": 120,
   "n": 4,
   "d": 4,
   "bt": [4, 4, 4, 4]
  },
  {
   "t": 112000,
   "b": 208.1,
   "bpm": 113,
   "n": 4,
   "d": 4,
   "bt": [4, 4, 4, 4]
  },
  {
   "t": 113000,
   "b": 209.9833,
   "bpm": 108,
   "n": 4,
   "d": 4,
   "bt": [4, 4, 4, 4]
  },
  {
   "t": 114000,
   "b": 211.7833,
   "bpm": 120,
   "n": 4,
   "d": 4,
   "bt": [4, 4, 4, 4]
  },
  {
   "t": 122000,
   "b": 227.7833,
   "bpm": 130,
   "n": 4,
   "d": 4,
   "bt": [4, 4, 4, 4]
  }
 ]
}